{"HomeGoalScorer": [{"Player": "Chris Smalling", "Time": "22", "Type": "Goal"}, {"Player": "Juan Mata", "Time": "37", "Type": "Goal"}, {"Player": "Marcus Rashford", "Time": "40", "Type": "Goal"}, {"Player": "Paul Pogba", "Time": "42", "Type": "Goal"}], "AwayGoalScorer": [{"Player": "Demarai Gray", "Time": "59", "Type": "Goal"}], "HomeTeamFouls": [], "AwayTeamFouls": [], "HomeTeamAssist": [{"Time": ["22", "42"], "Player": "Daley Blind"}, {"Time": ["37"], "Player": "Jesse Lingard"}, {"Time": ["40"], "Player": "Juan Mata"}], "AwayTeamAssist": [{"Time": ["59"], "Player": "Daniel Amartey"}], "Referee": "Mike Dean", "Stadium": "Old Trafford, Manchester", "TotalHomeGoals": "4", "TotalAwayGoals": "1", "HomeTeam": "Manchester United", "AwayTeam": "Leicester City"}