{"HomeGoalScorer": [{"Player": "Pedro", "Time": "1", "Type": "Goal"}, {"Player": "Gary Cahill", "Time": "21", "Type": "Goal"}, {"Player": "Eden Hazard", "Time": "62", "Type": "Goal"}, {"Player": "N", "Time": "GoloKant\u00e9", "Type": "Goal"}], "AwayGoalScorer": [], "HomeTeamFouls": [], "AwayTeamFouls": [], "HomeTeamAssist": [{"Time": ["1"], "Player": "Marcos Alonso"}, {"Time": ["62"], "Player": "Nemanja Matic"}, {"Time": ["70"], "Player": "Pedro"}], "AwayTeamAssist": [], "Referee": "Martin Atkinson", "Stadium": "Stamford Bridge, London", "TotalHomeGoals": "4", "TotalAwayGoals": "0", "HomeTeam": "Chelsea", "AwayTeam": "Manchester United"}