{"HomeGoalScorer": [{"Player": "Wilfried Bony", "Time": "3", "Type": "Goal"}, {"Player": "Alfie Mawson", "Time": "55", "Type": "Goal"}], "AwayGoalScorer": [{"Player": "Wayne Routledge", "Time": "8", "Type": "Goal"}], "HomeTeamFouls": [], "AwayTeamFouls": [], "HomeTeamAssist": [{"Time": ["3", "73"], "Player": "Joe Allen"}], "AwayTeamAssist": [{"Time": ["8"], "Player": "Gylfi Sigurdsson"}], "Referee": "Michael Oliver", "Stadium": "bet365 Stadium, Stoke", "TotalHomeGoals": "3", "TotalAwayGoals": "1", "HomeTeam": "Stoke City", "AwayTeam": "Swansea City"}