{"HomeGoalScorer": [{"Player": "Joshua King", "Time": "48", "Type": "Goal"}, {"Player": "Benik Afobe", "Time": "82", "Type": "Goal"}], "AwayGoalScorer": [{"Player": "Christian Kabasele", "Time": "24", "Type": "Goal"}, {"Player": "Troy Deeney", "Time": "64", "Type": "Goal"}], "HomeTeamFouls": [], "AwayTeamFouls": [], "HomeTeamAssist": [{"Time": ["48"], "Player": "Adam Smith"}, {"Time": ["82"], "Player": "Andrew Surman"}], "AwayTeamAssist": [{"Time": ["24"], "Player": "Miguel Britos"}, {"Time": ["64"], "Player": "Tom Cleverley"}], "Referee": "Lee Mason", "Stadium": "Vitality Stadium, Bournemouth", "TotalHomeGoals": "2", "TotalAwayGoals": "2", "HomeTeam": "AFC Bournemouth", "AwayTeam": "Watford"}