{"HomeGoalScorer": [], "AwayGoalScorer": [{"Player": "Vincent Kompany", "Time": "55", "Type": "Goal"}, {"Player": "Leroy San\u00e9", "Time": "77", "Type": "Goal"}, {"Player": "Sergio Ag\u00fcero", "Time": "80", "Type": "Goal"}], "HomeTeamFouls": [], "AwayTeamFouls": [], "HomeTeamAssist": [], "AwayTeamAssist": [{"Time": ["55"], "Player": "David Silva"}, {"Time": ["77", "80"], "Player": "Kevin De Bruyne"}], "Referee": "Neil Swarbrick", "Stadium": "St. Mary's Stadium, Southampton", "TotalHomeGoals": "0", "TotalAwayGoals": "3", "HomeTeam": "Southampton", "AwayTeam": "Manchester City"}